<?xml version="1.0" encoding="utf-8" ?><dwsync><file name="form-attachment.php" server="173.201.233.1" local="3646330439" remote="3646296000" Dst="-1" /><file name="form-comment.php" server="173.201.233.1" local="3646330439" remote="3646296000" Dst="-1" /><file name="form-customizer.php" server="173.201.233.1" local="3646330442" remote="3646296000" Dst="-1" /><file name="form-front.php" server="173.201.233.1" local="3646330442" remote="3646296000" Dst="-1" /><file name="form-gutenberg.php" server="173.201.233.1" local="3646330446" remote="3646296000" Dst="-1" /><file name="form-nav-menu.php" server="173.201.233.1" local="3646330443" remote="3646296000" Dst="-1" /><file name="form-post.php" server="173.201.233.1" local="3646330443" remote="3646296000" Dst="-1" /><file name="form-taxonomy.php" server="173.201.233.1" local="3646330446" remote="3646296000" Dst="-1" /><file name="form-user.php" server="173.201.233.1" local="3646330449" remote="3646296000" Dst="-1" /><file name="form-widget.php" server="173.201.233.1" local="3646330449" remote="3646296000" Dst="-1" /></dwsync>